setup.py
fourmi/__init__.py
fourmi/fourmi.py
fourmi.egg-info/PKG-INFO
fourmi.egg-info/SOURCES.txt
fourmi.egg-info/dependency_links.txt
fourmi.egg-info/top_level.txt